{
  "$schema": "http://json-schema.org/draft-07/schema#",
  "type": "object",
  "required": [],
  "properties": {
    "status": {
      "type": "string",
      "enum": [
        "offered",
        "settled",
        "local_failed",
        "failed"
      ]
    },
    "in_channel": {
      "type": "short_channel_id"
    },
    "out_channel": {
      "type": "short_channel_id"
    },
    "index": {
      "type": "string",
      "added": "v23.11",
      "enum": [
        "created",
        "updated"
      ],
      "description": ""
    },
    "start": {
      "type": "u64",
      "added": "v23.11",
      "description": ""
    },
    "limit": {
      "type": "u32",
      "added": "v23.11",
      "description": ""
    }
  }
}
